switchai/__init__.py
switchai/base_client.py
switchai/main_client.py
switchai/types.py
switchai/utils.py
switchai/providers/__init__.py
switchai/providers/_anthropic.py
switchai/providers/_deepgram.py
switchai/providers/_deepseek.py
switchai/providers/_google.py
switchai/providers/_mistral.py
switchai/providers/_ollama.py
switchai/providers/_openai.py
switchai/providers/_replicate.py
switchai/providers/_voyageai.py
switchai/providers/_xai.py
switchai/providers/x_cohere.py
switchai/superclients/__init__.py
switchai/superclients/browser.py
switchai/superclients/classifier.py
switchai/superclients/illustrator.py
switchai/superclients/image_retriever.py
switchai/superclients/slide_maker.py
switchai-0.6.1.dist-info/LICENSE
switchai-0.6.1.dist-info/METADATA
switchai-0.6.1.dist-info/WHEEL
switchai-0.6.1.dist-info/top_level.txt
switchai-0.6.1.dist-info/RECORD
