Metadata-Version: 2.2
Name: switchai
Version: 0.6.1
Summary: A unified library for interacting with various AI APIs through a standardized interface.
Home-page: https://github.com/yelboudouri/SwitchAI
Author: Yassine El Boudouri
Author-email: boudouriyassine@gmail.com
License: Apache 2.0 License
Classifier: Intended Audience :: Developers
Classifier: Intended Audience :: Education
Classifier: Intended Audience :: Science/Research
Classifier: Operating System :: OS Independent
Classifier: Topic :: Scientific/Engineering :: Artificial Intelligence
Requires-Python: >=3.6
License-File: LICENSE
Requires-Dist: pydantic
Requires-Dist: Pillow
Requires-Dist: httpx
Requires-Dist: numpy
Requires-Dist: cairosvg
Requires-Dist: openai
Requires-Dist: mistralai
Requires-Dist: anthropic
Requires-Dist: google-generativeai
Requires-Dist: deepgram-sdk
Requires-Dist: voyageai
Requires-Dist: replicate
Requires-Dist: ollama
Dynamic: author
Dynamic: author-email
Dynamic: classifier
Dynamic: description
Dynamic: description-content-type
Dynamic: home-page
Dynamic: license
Dynamic: requires-dist
Dynamic: requires-python
Dynamic: summary
